{
  "formatVersion": 1,
  "database": {
    "version": 2,
    "identityHash": "4688a6ff1d773521010ac531f2160268",
    "entities": [
      {
        "tableName": "credentials",
        "createSql": "CREATE TABLE IF NOT EXISTS `${TABLE_NAME}` (`id` INTEGER PRIMARY KEY AUTOINCREMENT, `username` TEXT, `password` TEXT, `sessionResource` TEXT, `deviceClientId` BLOB)",
        "fields": [
          {
            "fieldPath": "id",
            "columnName": "id",
            "affinity": "INTEGER",
            "notNull": false
          },
          {
            "fieldPath": "username",
            "columnName": "username",
            "affinity": "TEXT",
            "notNull": false
          },
          {
            "fieldPath": "password",
            "columnName": "password",
            "affinity": "TEXT",
            "notNull": false
          },
          {
            "fieldPath": "sessionResource",
            "columnName": "sessionResource",
            "affinity": "TEXT",
            "notNull": false
          },
          {
            "fieldPath": "deviceClientId",
            "columnName": "deviceClientId",
            "affinity": "BLOB",
            "notNull": false
          }
        ],
        "primaryKey": {
          "autoGenerate": true,
          "columnNames": [
            "id"
          ]
        },
        "indices": [],
        "foreignKeys": []
      },
      {
        "tableName": "account",
        "createSql": "CREATE TABLE IF NOT EXISTS `${TABLE_NAME}` (`id` INTEGER PRIMARY KEY AUTOINCREMENT, `credentialsId` INTEGER NOT NULL, `accountId` TEXT, `name` TEXT, `selected` INTEGER NOT NULL, FOREIGN KEY(`credentialsId`) REFERENCES `credentials`(`id`) ON UPDATE NO ACTION ON DELETE CASCADE )",
        "fields": [
          {
            "fieldPath": "id",
            "columnName": "id",
            "affinity": "INTEGER",
            "notNull": false
          },
          {
            "fieldPath": "credentialsId",
            "columnName": "credentialsId",
            "affinity": "INTEGER",
            "notNull": true
          },
          {
            "fieldPath": "accountId",
            "columnName": "accountId",
            "affinity": "TEXT",
            "notNull": false
          },
          {
            "fieldPath": "name",
            "columnName": "name",
            "affinity": "TEXT",
            "notNull": false
          },
          {
            "fieldPath": "selected",
            "columnName": "selected",
            "affinity": "INTEGER",
            "notNull": true
          }
        ],
        "primaryKey": {
          "autoGenerate": true,
          "columnNames": [
            "id"
          ]
        },
        "indices": [
          {
            "name": "index_account_credentialsId",
            "unique": false,
            "columnNames": [
              "credentialsId"
            ],
            "orders": [],
            "createSql": "CREATE INDEX IF NOT EXISTS `index_account_credentialsId` ON `${TABLE_NAME}` (`credentialsId`)"
          }
        ],
        "foreignKeys": [
          {
            "table": "credentials",
            "onDelete": "CASCADE",
            "onUpdate": "NO ACTION",
            "columns": [
              "credentialsId"
            ],
            "referencedColumns": [
              "id"
            ]
          }
        ]
      },
      {
        "tableName": "search_suggestion",
        "createSql": "CREATE TABLE IF NOT EXISTS `${TABLE_NAME}` (`id` INTEGER, `query` TEXT, PRIMARY KEY(`id`))",
        "fields": [
          {
            "fieldPath": "id",
            "columnName": "id",
            "affinity": "INTEGER",
            "notNull": false
          },
          {
            "fieldPath": "query",
            "columnName": "query",
            "affinity": "TEXT",
            "notNull": false
          }
        ],
        "primaryKey": {
          "autoGenerate": false,
          "columnNames": [
            "id"
          ]
        },
        "indices": [
          {
            "name": "index_search_suggestion_query",
            "unique": true,
            "columnNames": [
              "query"
            ],
            "orders": [],
            "createSql": "CREATE UNIQUE INDEX IF NOT EXISTS `index_search_suggestion_query` ON `${TABLE_NAME}` (`query`)"
          }
        ],
        "foreignKeys": []
      }
    ],
    "views": [],
    "setupQueries": [
      "CREATE TABLE IF NOT EXISTS room_master_table (id INTEGER PRIMARY KEY,identity_hash TEXT)",
      "INSERT OR REPLACE INTO room_master_table (id,identity_hash) VALUES(42, '4688a6ff1d773521010ac531f2160268')"
    ]
  }
}